recollwebui/bottle.py
recollwebui/conftree.py
recollwebui/standalone.py
recollwebui/static/extra.js
recollwebui/static/jdpicker.css
recollwebui/static/jdpicker.js
recollwebui/static/jquery.js
recollwebui/static/recoll.png
recollwebui/static/style.css
recollwebui/views/footer.tpl
recollwebui/views/header.tpl
recollwebui/views/main.tpl
recollwebui/views/osd.tpl
recollwebui/views/pages.tpl
recollwebui/views/result.tpl
recollwebui/views/results.tpl
recollwebui/views/search.tpl
recollwebui/views/settings.tpl
recollwebui/webui-wsgi.py
recollwebui/webui.py
recollwebui-0.1.2.dist-info/METADATA
recollwebui-0.1.2.dist-info/entry_points.txt
recollwebui-0.1.2.dist-info/WHEEL
recollwebui-0.1.2.dist-info/RECORD
