Metadata-Version: 2.1
Name: recollwebui
Version: 0.1.2
Summary: Web interface for recoll desktop search
Home-page: https://framagit.org/medoc92/recollwebui
Author: Jean-Francois Dockes
Author-email: jf@dockes.org
Requires-Python: >=3.7,<4.0
Classifier: Programming Language :: Python :: 3
Classifier: Programming Language :: Python :: 3.7
Classifier: Programming Language :: Python :: 3.8
Classifier: Programming Language :: Python :: 3.9
Classifier: Programming Language :: Python :: 3.10
Classifier: Programming Language :: Python :: 3.11
Requires-Dist: waitress (>=2.1.2,<3.0.0)
Project-URL: Repository, https://framagit.org/medoc92/recollwebui
